[
  {
    "id": "SEATING_GT_200",
    "condition": {
      "seating_gt": 200
    },
    "requirement": "לעסק עם מעל 200 מקומות ישיבה יש דרישות מיוחדות"
  },
  {
    "id": "SEATING_LTE_200",
    "condition": {
      "seating_lte": 200,
      "alcohol": false
    },
    "requirement": "עסק עד 200 מקומות ישיבה ללא מכירת/הגשת/צריכת אלכוהול פטור מדרישות מסוימות"
  },
  {
    "id": "FEATURE_HOT_PREP",
    "condition": {
      "features": [
        "meat",
        "fish"
      ]
    },
    "requirement": "לבשל בשר/עופות/דגים עד חימום מלא (72°C למשך 2 דקות בנקודה הקרה), לקרר במהירות אם מוגש קר, ולאחסן בטמפרטורות מתאימות"
  },
  {
    "id": "FEATURE_GAS_LPG",
    "condition": {
      "features": [
        "gas"
      ]
    },
    "requirement": "מערכת גפ\"מ וציוד נלווים במצב תקין ומתוחזק; לשמור בעסק אישורים (מטפים לפי ת\"י 129/1, בדיקת חשמל/תאורות חירום)."
  }
]